yamlip.py
yamlip-0.0.2.dist-info/LICENSE
yamlip-0.0.2.dist-info/METADATA
yamlip-0.0.2.dist-info/WHEEL
yamlip-0.0.2.dist-info/entry_points.txt
yamlip-0.0.2.dist-info/top_level.txt
yamlip-0.0.2.dist-info/RECORD
